splunk_data_sender/__init__.py
splunk_data_sender/test.py
splunk_data_sender-0.5.0.dist-info/LICENSE
splunk_data_sender-0.5.0.dist-info/METADATA
splunk_data_sender-0.5.0.dist-info/WHEEL
splunk_data_sender-0.5.0.dist-info/top_level.txt
splunk_data_sender-0.5.0.dist-info/RECORD
