Metadata-Version: 2.1
Name: splunk-data-sender
Version: 0.5.0
Summary: A Python connector that sends your data to Splunk via HEC
Author-email: Andrea Salvatori <16443598+Sonic0@users.noreply.github.com>
Project-URL: Homepage, https://github.com/Sonic0/splunk-data-sender
Project-URL: Issues, https://github.com/Sonic0/splunk-data-sender/issues
Classifier: Development Status :: 4 - Beta
Classifier: Intended Audience :: Developers
Classifier: License :: OSI Approved :: MIT License
Classifier: Natural Language :: English
Classifier: Operating System :: POSIX :: Linux
Classifier: Operating System :: MacOS :: MacOS X
Classifier: Programming Language :: Python :: 3
Classifier: Programming Language :: Python :: 3 :: Only
Classifier: Topic :: System :: Logging
Requires-Python: >=3.8
License-File: LICENSE
Requires-Dist: requests <3.0.0,>=2.27.0
